DetectVideoShotLength/__init__.py
DetectVideoShotLength/main.py
DetectVideoShotLength-0.12.dist-info/LICENSE
DetectVideoShotLength-0.12.dist-info/METADATA
DetectVideoShotLength-0.12.dist-info/WHEEL
DetectVideoShotLength-0.12.dist-info/top_level.txt
DetectVideoShotLength-0.12.dist-info/RECORD
