Metadata-Version: 2.1
Name: DetectVideoShotLength
Version: 0.12
Summary: A lightweight python package that analyzes shot lengths for video.
Author: Rakib Mollah
Author-email: rakib1703115@gmail.com
License: MIT
Classifier: License :: OSI Approved :: MIT License
Classifier: Programming Language :: Python :: 3.10
Classifier: Operating System :: OS Independent
License-File: LICENSE
Requires-Dist: bson >=0.5.10
Requires-Dist: opencv-python
Requires-Dist: numpy
Requires-Dist: matplotlib
Requires-Dist: tqdm
Requires-Dist: scikit-image
